[{"nammo":"United Cup","venue":"Perth-Sydney, Australia | ","date":"27 December, 2024 - 5 January, 2025","scraped_date_month":"2025_01"},{"nammo":"Brisbane International presented by Evie","venue":"Brisbane, Australia | ","date":"29 December, 2024 - 5 January, 2025","scraped_date_month":"2025_01"},{"nammo":"Bank of China Hong Kong Tennis Open","venue":"Hong Kong, Hong Kong | ","date":"30 December, 2024 - 5 January, 2025","scraped_date_month":"2025_01"},{"nammo":"Adelaide International","venue":"Adelaide, Australia | ","date":"6 - 11 January, 2025","scraped_date_month":"2025_01"},{"nammo":"ASB Classic","venue":"Auckland, New Zealand | ","date":"6 - 11 January, 2025","scraped_date_month":"2025_01"},{"nammo":"Australian Open","venue":"Melbourne, Australia | ","date":"12 - 26 January, 2025","scraped_date_month":"2025_01"},{"nammo":"Open Occitanie","venue":"Montpellier, France | ","date":"27 January - 2 February, 2025","scraped_date_month":"2025_01"},{"nammo":"Davis Cup Qualifiers 1st Roun","venue":"Multiple Locations | ","date":"31 January - 2 February, 2025","scraped_date_month":"2025_01"},{"nammo":"ABN AMRO Open","venue":"Rotterdam, Netherlands | ","date":"3 - 9 February, 2025","scraped_date_month":"2025_01"},{"nammo":"Dallas Open","venue":"Dallas, United States | ","date":"3 - 9 February, 2025","scraped_date_month":"2025_01"},{"nammo":"Delray Beach Open","venue":"Delray Beach, United States | ","date":"10 - 16 February, 2025","scraped_date_month":"2025_01"},{"nammo":"IEB+ Argentina Open","venue":"Buenos Aires, Argentina | ","date":"10 - 16 February, 2025","scraped_date_month":"2025_01"},{"nammo":"Open 13 Provence","venue":"Marseille, France | ","date":"10 - 16 February, 2025","scraped_date_month":"2025_01"},{"nammo":"Qatar ExxonMobil Open","venue":"Doha, Qatar | ","date":"17 - 22 February, 2025","scraped_date_month":"2025_01"},{"nammo":"Rio Open presented by Claro","venue":"Rio de Janeiro, Brazil | ","date":"17 - 23 February, 2025","scraped_date_month":"2025_01"},{"nammo":"Abierto Mexicano Telcel presentado por HSBC","venue":"Acapulco, Mexico | ","date":"24 February - 1 March, 2025","scraped_date_month":"2025_01"},{"nammo":"Dubai Duty Free Tennis Championships","venue":"Dubai, United Arab Emirates | ","date":"24 February - 1 March, 2025","scraped_date_month":"2025_01"},{"nammo":"Movistar Chile Open","venue":"Santiago, Chile | ","date":"24 February - 2 March, 2025","scraped_date_month":"2025_01"},{"nammo":"BNP Paribas Open","venue":"Indian Wells, United States | ","date":"5 - 16 March, 2025","scraped_date_month":"2025_01"},{"nammo":"Miami Open presented by Itau","venue":"Miami, United States | ","date":"19 - 30 March, 2025","scraped_date_month":"2025_01"},{"nammo":"Fayez Sarofim & Co. U.S. Men's Clay Court Championship","venue":"Houston, United States | ","date":"31 March - 6 April, 2025","scraped_date_month":"2025_01"},{"nammo":"Grand Prix Hassan II","venue":"Marrakech, Morocco | ","date":"31 March - 6 April, 2025","scraped_date_month":"2025_01"},{"nammo":"Tiriac Open","venue":"Bucharest, Romania | ","date":"31 March - 6 April, 2025","scraped_date_month":"2025_01"},{"nammo":"Rolex Monte-Carlo Masters","venue":"Monte-Carlo, Monaco | ","date":"6 - 13 April, 2025","scraped_date_month":"2025_01"},{"nammo":"Barcelona Open Banc Sabadell","venue":"Barcelona, Spain | ","date":"14 - 20 April, 2025","scraped_date_month":"2025_01"},{"nammo":"BMW Open","venue":"Munich, Germany | ","date":"14 - 20 April, 2025","scraped_date_month":"2025_01"},{"nammo":"Mutua Madrid Open","venue":"Madrid, Spain | ","date":"23 April - 4 May, 2025","scraped_date_month":"2025_01"},{"nammo":"Internazionali BNL d'Italia","venue":"Rome, Italy | ","date":"7 - 18 May, 2025","scraped_date_month":"2025_01"},{"nammo":"Gonet Geneva Open","venue":"Geneva, Switzerland | ","date":"18 - 24 May, 2025","scraped_date_month":"2025_01"},{"nammo":"Hamburg Open","venue":"Hamburg, Germany | ","date":"18 - 24 May, 2025","scraped_date_month":"2025_01"},{"nammo":"Roland Garros","venue":"Paris, France | ","date":"25 May - 8 June, 2025","scraped_date_month":"2025_01"},{"nammo":"BOSS OPEN","venue":"Stuttgart, Germany | ","date":"9 - 15 June, 2025","scraped_date_month":"2025_01"},{"nammo":"Libema Open","venue":"'s-Hertogenbosch, Netherlands | ","date":"9 - 15 June, 2025","scraped_date_month":"2025_01"},{"nammo":"cinch Championships","venue":"London, Great Britain | ","date":"16 - 22 June, 2025","scraped_date_month":"2025_01"},{"nammo":"Terra Wortmann Open","venue":"Halle, Germany | ","date":"16 - 22 June, 2025","scraped_date_month":"2025_01"},{"nammo":"Mallorca Championships presented by Waterdrop","venue":"Mallorca, Spain | ","date":"22 - 28 June, 2025","scraped_date_month":"2025_01"},{"nammo":"Rothesay International","venue":"Eastbourne, Great Britain | ","date":"23 - 28 June, 2025","scraped_date_month":"2025_01"},{"nammo":"Wimbledon","venue":"London, Great Britain | ","date":"30 June - 13 July, 2025","scraped_date_month":"2025_01"},{"nammo":"EFG Swiss Open Gstaad","venue":"Gstaad, Switzerland | ","date":"14 - 20 July, 2025","scraped_date_month":"2025_01"},{"nammo":"Mifel Tennis Open by Telcel Oppo","venue":"Los Cabos, Mexico | ","date":"14 - 19 July, 2025","scraped_date_month":"2025_01"},{"nammo":"Nordea Open","venue":"Bastad, Sweden | ","date":"14 - 20 July, 2025","scraped_date_month":"2025_01"},{"nammo":"Generali Open","venue":"Kitzbuhel, Austria | ","date":"20 - 26 July, 2025","scraped_date_month":"2025_01"},{"nammo":"Plava Laguna Croatia Open Umag","venue":"Umag, Croatia | ","date":"20 - 26 July, 2025","scraped_date_month":"2025_01"},{"nammo":"Mubadala Citi DC Open","venue":"Washington, United States | ","date":"21 - 27 July, 2025","scraped_date_month":"2025_01"},{"nammo":"National Bank Open Presented by Rogers","venue":"Toronto, Canada | ","date":"27 July - 7 August, 2025","scraped_date_month":"2025_01"},{"nammo":"Cincinnati Open","venue":"Cincinnati, United States | ","date":"7 - 18 August, 2025","scraped_date_month":"2025_01"},{"nammo":"Winston-Salem Open","venue":"Winston-Salem, United States | ","date":"17 - 23 August, 2025","scraped_date_month":"2025_01"},{"nammo":"US Open","venue":"New York, United States | ","date":"25 August - 7 September, 2025","scraped_date_month":"2025_01"},{"nammo":"Davis Cup Qualifiers 2nd Roun","venue":"Multiple Locations | ","date":"12 - 14 September, 2025","scraped_date_month":"2025_01"},{"nammo":"Chengdu Open","venue":"Chengdu, China | ","date":"17 - 23 September, 2025","scraped_date_month":"2025_01"},{"nammo":"Hangzhou Open","venue":"Hangzhou, China | ","date":"17 - 23 September, 2025","scraped_date_month":"2025_01"},{"nammo":"Laver Cup","venue":"San Francisco, United States | ","date":"19 - 21 September, 2025","scraped_date_month":"2025_01"},{"nammo":"Kinoshita Group Japan Open Tennis Championships","venue":"Tokyo, Japan | ","date":"24 - 30 September, 2025","scraped_date_month":"2025_01"},{"nammo":"China Open","venue":"Beijing, China | ","date":"25 September - 1 October, 2025","scraped_date_month":"2025_01"},{"nammo":"Rolex Shanghai Masters","venue":"Shanghai, China | ","date":"1 - 12 October, 2025","scraped_date_month":"2025_01"},{"nammo":"Almaty Open","venue":"Almaty, Kazakhstan | ","date":"13 - 19 October, 2025","scraped_date_month":"2025_01"},{"nammo":"BNP Paribas Nordic Open","venue":"Stockholm, Sweden | ","date":"13 - 19 October, 2025","scraped_date_month":"2025_01"},{"nammo":"European Open","venue":"Antwerp, Belgium | ","date":"13 - 19 October, 2025","scraped_date_month":"2025_01"},{"nammo":"Erste Bank Open","venue":"Vienna, Austria | ","date":"20 - 26 October, 2025","scraped_date_month":"2025_01"},{"nammo":"Swiss Indoors Basel","venue":"Basel, Switzerland | ","date":"20 - 26 October, 2025","scraped_date_month":"2025_01"},{"nammo":"Rolex Paris Masters","venue":"Paris, France | ","date":"27 October - 2 November, 2025","scraped_date_month":"2025_01"},{"nammo":"Belgrade Open","venue":"Belgrade, Serbia | ","date":"2 - 8 November, 2025","scraped_date_month":"2025_01"},{"nammo":"Moselle Open","venue":"Metz, France | ","date":"2 - 8 November, 2025","scraped_date_month":"2025_01"},{"nammo":"Nitto ATP Finals","venue":"Turin, Italy | ","date":"9 - 16 November, 2025","scraped_date_month":"2025_01"},{"nammo":"Davis Cup Finals","venue":"Bologna, Spain | ","date":"17 - 23 November, 2025","scraped_date_month":"2025_01"}]